{
  "id": "albedo",
  "ascensionStats": [
    {
      "level": 1,
      "baseHp": 1030,
      "baseAtk": 20,
      "baseDef": 68,
      "bonus": 0,
      "isAscension": false
    },
    {
      "level": 20,
      "baseHp": 2671,
      "baseAtk": 51,
      "baseDef": 177,
      "bonus": 0,
      "isAscension": false
    },
    {
      "level": 20,
      "baseHp": 3554,
      "baseAtk": 67,
      "baseDef": 235,
      "bonus": 0,
      "isAscension": true
    },
    {
      "level": 40,
      "baseHp": 5317,
      "baseAtk": 101,
      "baseDef": 352,
      "bonus": 0,
      "isAscension": false
    },
    {
      "level": 40,
      "baseHp": 5944,
      "baseAtk": 113,
      "baseDef": 394,
      "bonus": 7.2,
      "isAscension": true
    },
    {
      "level": 50,
      "baseHp": 6839,
      "baseAtk": 130,
      "baseDef": 453,
      "bonus": 7.2,
      "isAscension": false
    },
    {
      "level": 50,
      "baseHp": 7675,
      "baseAtk": 146,
      "baseDef": 508,
      "bonus": 14.4,
      "isAscension": true
    },
    {
      "level": 60,
      "baseHp": 8579,
      "baseAtk": 163,
      "baseDef": 568,
      "bonus": 14.4,
      "isAscension": false
    },
    {
      "level": 60,
      "baseHp": 9207,
      "baseAtk": 175,
      "baseDef": 610,
      "bonus": 14.4,
      "isAscension": true
    },
    {
      "level": 70,
      "baseHp": 10119,
      "baseAtk": 192,
      "baseDef": 670,
      "bonus": 14.4,
      "isAscension": false
    },
    {
      "level": 70,
      "baseHp": 10746,
      "baseAtk": 204,
      "baseDef": 712,
      "bonus": 21.6,
      "isAscension": true
    },
    {
      "level": 80,
      "baseHp": 11669,
      "baseAtk": 222,
      "baseDef": 773,
      "bonus": 21.6,
      "isAscension": false
    },
    {
      "level": 80,
      "baseHp": 12296,
      "baseAtk": 233,
      "baseDef": 815,
      "bonus": 28.8,
      "isAscension": true
    },
    {
      "level": 90,
      "baseHp": 13226,
      "baseAtk": 251,
      "baseDef": 876,
      "bonus": 28.8,
      "isAscension": false
    }
  ],
  "ascensionMaterials": [
    {
      "level": 1,
      "materials": [
        {
					"image": "currency/mora",
          "amount": 20000
        },
        {
					"image": "character_ascension/prithiva_topaz_sliver",
          "amount": 1
        },
        {
					"image": "local/cecilia",
          "amount": 3
        },
        {
					"image": "common/divining_scroll",
          "amount": 3
        }
      ]
    },
    {
      "level": 2,
      "materials": [
        {
					"image": "currency/mora",
          "amount": 40000
        },
        {
					"image": "character_ascension/prithiva_topaz_fragment",
          "amount": 3
        },
        {
					"image": "character_ascension/basalt_pillar",
          "amount": 2
        },
        {
					"image": "local/cecilia",
          "amount": 10
        },
        {
					"image": "common/divining_scroll",
          "amount": 15
        }
      ]
    },
    {
      "level": 3,
      "materials": [
        {
					"image": "currency/mora",
          "amount": 60000
        },
        {
          "image": "character_ascension/prithiva_topaz_fragment",
          "amount": 6
        },
        {
          "image": "character_ascension/basalt_pillar",
          "amount": 4
        },
        {
          "image": "local/cecilia",
          "amount": 20
        },
        {
					"image": "common/sealed_scroll",
          "amount": 12
        }
      ]
    },
    {
      "level": 4,
      "materials": [
        {
          "image": "currency/mora",
          "amount": 80000
        },
        {
					"image": "character_ascension/prithiva_topaz_chunk",
          "amount": 3
        },
        {
          "image": "character_ascension/basalt_pillar",
          "amount": 8
        },
        {
          "image": "local/cecilia",
          "amount": 30
        },
        {
          "image": "common/sealed_scroll",
          "amount": 18
        }
      ]
    },
    {
      "level": 5,
      "materials": [
        {
          "image": "currency/mora",
          "amount": 100000
        },
        {
          "image": "character_ascension/prithiva_topaz_chunk",
          "amount": 6
        },
        {
          "image": "character_ascension/basalt_pillar",
          "amount": 12
        },
        {
          "image": "local/cecilia",
          "amount": 45
        },
        {
					"image": "common/forbidden_curse_scroll",
          "amount": 12
        }
      ]
    },
    {
      "level": 6,
      "materials": [
        {
          "image": "currency/mora",
          "amount": 120000
        },
        {
					"image": "character_ascension/prithiva_topaz_gemstone",
          "amount": 6
        },
        {
          "image": "character_ascension/basalt_pillar",
          "amount": 20
        },
        {
          "image": "local/cecilia",
          "amount": 60
        },
        {
          "image": "common/forbidden_curse_scroll",
          "amount": 24
        }
      ]
    }
  ],
	"talentStats": [
		[
			[[36.7], [39.7], [42.7],	[47],	[50],	[53.4],	[58.1],	[62.8],	[67.5],	[72.6],	[78.5],	[85.4],	[92.3]],
			[[36.7], [39.7], [42.7],	[47],	[50],	[53.4],	[58.1],	[62.8],	[67.5],	[72.6],	[78.5],	[85.4],	[92.3]],
			[[47.5],	[51.3],	[55.2],	[60.7],	[64.6],	[69],	[75],	[81.1],	[87.2],	[93.8],	[101.4], [110.3], [119.2]],
			[[49.8], [53.8], [57.8], [63.6], [67.7], [72.3], [78.7], [85], [91.4], [98.3], [106.3], [115.7], [125]],
			[[62.1],	[67.1],	[72.2],	[79.4],	[84.4],	[90.2],	[98.2],	[106.1], [114],	[122.7], [132.6],	[144.3], [156]],
			[[47.3, 60.2],	[51.2, 65.1],	[55, 70],	[60.5, 77],	[64.3, 81.9],	[68.8, 87.5],	[74.8, 95.2],	[80.8, 102.9], [86.9, 110.6],	[93.5, 119], [101.1, 128.6],	[110, 139.9],	[118.8, 151.3]],
			[[20],	[20],	[20],	[20],	[20],	[20],	[20],	[20],	[20],	[20],	[20],	[20],	[20]],
			[[63.9],	[69.1],	[74.3],	[81.8],	[87],	[92.9],	[101.1], [109.3], [117.5], [126.4], [135.3], [144.2], [153.1]],
			[[128, 160],	[138, 173],	[149, 186],	[164, 204],	[174, 217],	[186, 232],	[202, 253],	[219, 273],	[235, 293], [253, 316],	[271, 338],	[288, 360],	[306, 382]]
		],
		[
      [[130], [140], [150], [163], [173], [183], [196], [209], [222], [235], [248], [261], [277]],
      [[134], [144], [154], [167], [177], [187], [200], [214], [227], [240], [254], [267], [284]],
      [[30], [30], [30], [30], [30], [30], [30], [30], [30], [30], [30], [30], [30]],
      [[4], [4], [4], [4], [4], [4], [4], [4], [4], [4], [4], [4], [4]]
		],
    [
      [[367], [395], [422], [459], [487], [514], [551], [588], [624], [661], [698], [734], [780]],
      [[72], [77.4], [82.8], [90], [95.4], [100.8], [108], [115.2], [122.4], [129.6], [136.8], [144], [153]],
      [[12], [12], [12], [12], [12], [12], [12], [12], [12], [12], [12], [12], [12]],
      [[40], [40], [40], [40], [40], [40], [40], [40], [40], [40], [40], [40], [40]]
    ]
	],
  "talentMaterials": [
    {
      "level": 2,
      "materials": [
        {
					"image": "currency/mora",
          "amount": 12500
        },
        {
					"image": "talent/teachings_of_ballad",
          "amount": 3
        },
        {
					"image": "common/divining_scroll",
          "amount": 6
        }
      ]
    },
    {
      "level": 3,
      "materials": [
        {
					"image": "currency/mora",
          "amount": 17500
        },
        {
					"image": "talent/guide_to_ballad",
          "amount": 2
        },
        {
					"image": "common/sealed_scroll",
          "amount": 3
        }
      ]
    },
    {
      "level": 4,
      "materials": [
        {
					"image": "currency/mora",
          "amount": 25000
        },
        {
         	"image": "talent/guide_to_ballad",
          "amount": 4
        },
        {
          "image": "common/sealed_scroll",
          "amount": 4
        }
      ]
    },
    {
      "level": 5,
      "materials": [
        {
          "image": "currency/mora",
          "amount": 30000
        },
        {
          "image": "talent/guide_to_ballad",
          "amount": 6
        },
        {
          "image": "common/sealed_scroll",
          "amount": 6
        }
      ]
    },
    {
      "level": 6,
      "materials": [
        {
          "image": "currency/mora",
          "amount": 37500
        },
        {
          "image": "talent/guide_to_ballad",
          "amount": 9
        },
        {
          "image": "common/sealed_scroll",
          "amount": 9
        }
      ]
    },
    {
      "level": 7,
      "materials": [
        {
          "image": "currency/mora",
          "amount": 120000
        },
        {
					"image": "talent/philosophies_of_ballad",
          "amount": 4
        },
        {
					"image": "common/forbidden_curse_scroll",
          "amount": 4
        },
        {
					"image": "talent/tusk_of_monoceros_caeli",
          "amount": 1
        }
      ]
    },
    {
      "level": 8,
      "materials": [
        {
          "image": "currency/mora",
          "amount": 260000
        },
        {
          "image": "talent/philosophies_of_ballad",
          "amount": 6
        },
        {
          "image": "common/forbidden_curse_scroll",
          "amount": 6
        },
        {
          "image": "talent/tusk_of_monoceros_caeli",
          "amount": 1
        }
      ]
    },
    {
      "level": 9,
      "materials": [
        {
          "image": "currency/mora",
          "amount": 450000
        },
        {
          "image": "talent/philosophies_of_ballad",
          "amount": 12
        },
        {
          "image": "common/forbidden_curse_scroll",
          "amount": 9
        },
        {
          "image": "talent/tusk_of_monoceros_caeli",
          "amount": 2
        }
      ]
    },
    {
      "level": 10,
      "materials": [
        {
          "image": "currency/mora",
          "amount": 700000
        },
        {
          "image": "talent/philosophies_of_ballad",
          "amount": 16
        },
        {
          "image": "common/forbidden_curse_scroll",
          "amount": 12
        },
        {
          "image": "talent/tusk_of_monoceros_caeli",
          "amount": 2
        },
        {
					"image": "talent/crown_of_insight",
          "amount": 1
        }
      ]
    }
  ]
}